skyrouter/__init__.py
skyrouter/client.py
skyrouter/constants.py
skyrouter/enums.py
skyrouter/models.py
skyrouter-0.1.0.dist-info/LICENSE
skyrouter-0.1.0.dist-info/WHEEL
skyrouter-0.1.0.dist-info/METADATA
skyrouter-0.1.0.dist-info/RECORD
